gsnetact/__init__.py
gsnetact/GeneExpressions/__init__.py
gsnetact/GeneExpressions/geneExpScores.py
gsnetact/GeneSets/__init__.py
gsnetact/GeneSets/geneSetObjects.py
gsnetact/GeneSets/geneSetScores.py
gsnetact/Utils/MatrixItem.py
gsnetact/Utils/__init__.py
gsnetact/Utils/_annData.py
gsnetact/Utils/jsonParser.py
gsnetact/Utils/makeJsonFile.py
gsnetact-0.0.15.dist-info/METADATA
gsnetact-0.0.15.dist-info/WHEEL
gsnetact-0.0.15.dist-info/entry_points.txt
gsnetact-0.0.15.dist-info/top_level.txt
gsnetact-0.0.15.dist-info/RECORD
