Metadata-Version: 2.4
Name: gsnetact
Version: 0.0.15
Summary: The GSNetAct Python Package.
Dynamic: description
Dynamic: description-content-type
Dynamic: summary
